pyNuke/__init__.py
pyNuke/discordNuke.py
pyNuke/pyNuke.py
pyNuke/setup.py
pyNuke-1.2.3.dist-info/METADATA
pyNuke-1.2.3.dist-info/WHEEL
pyNuke-1.2.3.dist-info/top_level.txt
pyNuke-1.2.3.dist-info/RECORD
