Metadata-Version: 2.1
Name: pyNuke
Version: 1.2.3
Summary: A Discord Nuke. Meant to be used with good intent for testing purposes.
Home-page: UNKNOWN
Author: Tiago Coelho
Author-email: melaochapanao@gmail.com
License: The Unlicense
Platform: UNKNOWN
Classifier: Development Status :: 4 - Beta
Classifier: Intended Audience :: Developers
Classifier: Programming Language :: Python
Classifier: Programming Language :: Python :: 3
Classifier: Programming Language :: Python :: 3.6
Classifier: Programming Language :: Python :: 3.7
Classifier: Programming Language :: Python :: 3.8
Classifier: Programming Language :: Python :: 3.9
Requires-Dist: discord.py
